{"data":[{"updated_at":"2024-01-29T08:57:40+08:00","comment":null,"tags":[],"subject_id":390353,"vol_status":0,"ep_status":4,"subject_type":2,"type":3,"rate":0,"private":false,"date":"2024-01-06","images":{"small":"https://lain.bgm.tv/r/200/pic/cover/l/f5/2e/390353_07vz7.jpg","grid":"https://lain.bgm.tv/r/100/pic/cover/l/f5/2e/390353_07vz7.jpg","large":"https://lain.bgm.tv/pic/cover/l/f5/2e/390353_07vz7.jpg","medium":"https://lain.bgm.tv/r/800/pic/cover/l/f5/2e/390353_07vz7.jpg","common":"https://lain.bgm.tv/r/400/pic/cover/l/f5/2e/390353_07vz7.jpg"},"name":"俺だけレベルアップな件","name_cn":"我独自升级","summary":"连接异次元和现世界的通道“门”突然出现十来年后，世界上出现觉醒了超能力被称为“猎人”之人。\r\n猎人使用力量以攻占门内地下城并获得报酬为生，但在强者齐聚的猎人们中，“水篠旬”作为被称为人类最弱兵器的低等猎人而艰难生活。\r\n某日，水篠旬遭遇某个被隐藏在低等级迷宫中的高等级重迷宫，在身负濒死重伤的水篠旬面前出现了神秘的探索窗口。\r\n他在临死之际，决定接受任务之际，成为唯一能“升级”之人。","total_episodes":12,"eps":12},{"updated_at":"2024-01-29T07:16:50+08:00","comment":null,"tags":[],"subject_id":438187,"vol_status":0,"ep_status":3,"subject_type":2,"type":3,"rate":0,"private":false,"date":"2024-01-11","images":{"small":"https://lain.bgm.tv/r/200/pic/cover/l/3a/98/438187_zqjlu.jpg","grid":"https://lain.bgm.tv/r/100/pic/cover/l/3a/98/438187_zqjlu.jpg","large":"https://lain.bgm.tv/pic/cover/l/3a/98/438187_zqjlu.jpg","medium":"https://lain.bgm.tv/r/800/pic/cover/l/3a/98/438187_zqjlu.jpg","common":"https://lain.bgm.tv/r/400/pic/cover/l/3a/98/438187_zqjlu.jpg"},"name":"勇気爆発バーンブレイバーン","name_cn":"勇气爆发BangBravern","summary":"―――ふたりを繋ぐ“勇気”\r\n\r\n人型装甲兵器『ティタノストライド=通称TS（ティーエス）』が発達した時代。\r\n\r\n各国軍は“ハワイ オアフ島”に集結。\r\n陸上自衛隊所属 イサミ・アオと\r\nアメリカ海兵隊所属 ルイス・スミスのふたりは戦闘の最中出逢う。\r\n\r\n突如所属不明機による強襲を受け、為す術もなく散っていく兵士たち。\r\n\r\n己の誇りをかけて戦え。\r\n死と隣り合わせの戦場で生き残る為。\r\n仲間を救う為。\r\n\r\n命を信じて、“勇気”を燃やせ。","total_episodes":12,"eps":0},{"updated_at":"2024-01-23T15:11:46+08:00","comment":null,"tags":["MADHouse","2023年10月","漫画改","奇幻","公路片","旅行","漫改","2023","TV","治愈","催泪","未确定","2021年10月","2023年","异世界","日本动画","2020-2029"],"subject_id":400602,"vol_status":0,"ep_status":19,"subject_type":2,"type":3,"rate":0,"private":false,"date":"2023-09-29","images":{"small":"https://lain.bgm.tv/r/200/pic/cover/l/13/c5/400602_ZI8Y9.jpg","grid":"https://lain.bgm.tv/r/100/pic/cover/l/13/c5/400602_ZI8Y9.jpg","large":"https://lain.bgm.tv/pic/cover/l/13/c5/400602_ZI8Y9.jpg","medium":"https://lain.bgm.tv/r/800/pic/cover/l/13/c5/400602_ZI8Y9.jpg","common":"https://lain.bgm.tv/r/400/pic/cover/l/13/c5/400602_ZI8Y9.jpg"},"name":"葬送のフリーレン","name_cn":"葬送的芙莉莲","summary":"魔法使芙莉莲和勇者辛美尔等人一起，历经十年的冒险之后击败了魔王，为世界带来了和平。\r\n身为能活上一千多年的精灵族，她于是和辛美尔等人约定再次相见后，踏上了独自一人的旅途。\r\n自那以后，50年过去，芙莉莲又前往拜访辛美尔，相比于和50年前一点没变的她来说，辛美尔已经年迈体衰，进入了风烛残年。\r\n之后，她目睹了辛美尔迎来他的死亡，痛感自己以往没能“知晓人心\"，陷入后悔的芙莉莲，为了“知晓人心\"，踏上了旅途。\r\n这趟旅途会邂逅各种各样的人，也有各种各样的事情在等待着她。","total_episodes":34,"eps":28},{"updated_at":"2024-01-21T01:16:48+08:00","comment":null,"tags":[],"subject_id":436745,"vol_status":0,"ep_status":0,"subject_type":2,"type":3,"rate":0,"private":false,"date":"2024-01-13","images":{"small":"https://lain.bgm.tv/r/200/pic/cover/l/ce/d4/436745_I7n0N.jpg","grid":"https://lain.bgm.tv/r/100/pic/cover/l/ce/d4/436745_I7n0N.jpg","large":"https://lain.bgm.tv/pic/cover/l/ce/d4/436745_I7n0N.jpg","medium":"https://lain.bgm.tv/r/800/pic/cover/l/ce/d4/436745_I7n0N.jpg","common":"https://lain.bgm.tv/r/400/pic/cover/l/ce/d4/436745_I7n0N.jpg"},"name":"ぶっちぎり?!","name_cn":"","summary":"  ―逃げぬ心と見つけたり― \r\n灯荒仁は、かつての親友・浅観音真宝との\r\n再会をきっかけに強者たちの戦いに\r\n巻き込まれていく…。\r\nそんな中、巨大な魔人の影が現れ…？！ ","total_episodes":12,"eps":0},{"updated_at":"2024-01-20T12:37:04+08:00","comment":null,"tags":[],"subject_id":395378,"vol_status":0,"ep_status":2,"subject_type":2,"type":3,"rate":0,"private":false,"date":"2024-01-04","images":{"small":"https://lain.bgm.tv/r/200/pic/cover/l/c5/88/395378_1N3Zy.jpg","grid":"https://lain.bgm.tv/r/100/pic/cover/l/c5/88/395378_1N3Zy.jpg","large":"https://lain.bgm.tv/pic/cover/l/c5/88/395378_1N3Zy.jpg","medium":"https://lain.bgm.tv/r/800/pic/cover/l/c5/88/395378_1N3Zy.jpg","common":"https://lain.bgm.tv/r/400/pic/cover/l/c5/88/395378_1N3Zy.jpg"},"name":"ダンジョン飯","name_cn":"迷宫饭","summary":"「待ってろドラゴン、ステーキにしてやる！」\r\n\r\nダンジョンの奥深くでドラゴンに襲われ、金と食料を失ってしまった冒険者・ライオス一行。\r\n再びダンジョンに挑もうにも、このまま行けば、途中で飢え死にしてしまう。\r\nそこでライオスは決意する。「そうだ、モンスターを食べよう！」\r\nスライム、バジリスク、ミミック、そしてドラゴン！\r\n襲い来る凶暴なモンスターを食べながら、ダンジョンの踏破を目指せ！冒険者よ！","total_episodes":24,"eps":0},{"updated_at":"2023-12-12T12:33:33+08:00","comment":null,"tags":[],"subject_id":424663,"vol_status":0,"ep_status":0,"subject_type":2,"type":3,"rate":0,"private":false,"date":"2024-01-03","images":{"small":"https://lain.bgm.tv/r/200/pic/cover/l/96/d1/424663_mM5GN.jpg","grid":"https://lain.bgm.tv/r/100/pic/cover/l/96/d1/424663_mM5GN.jpg","large":"https://lain.bgm.tv/pic/cover/l/96/d1/424663_mM5GN.jpg","medium":"https://lain.bgm.tv/r/800/pic/cover/l/96/d1/424663_mM5GN.jpg","common":"https://lain.bgm.tv/r/400/pic/cover/l/96/d1/424663_mM5GN.jpg"},"name":"魔法少女にあこがれて","name_cn":"梦想成为魔法少女","summary":"わたし、柊うてなは魔法少女が大好きなごく普通の女の子☆\r\nある日、変身する力を与えてくれそうなマスコット的なやつに出会って不思議な魔法をかけられちゃった!\r\nこれでわたしも魔法少女に――と思ったら\r\nえ? なにこの格好?\r\n悪の組織の女幹部ってどういうこと!?\r\nこれからわたしどうなっちゃうの~~~!!?\r\n魔法少女ファンの心優しい内気な少女がサディスティックに大変身!!?\r\n正義と悪の激しい SM プレイ(!?)スタートです!!","total_episodes":13,"eps":13},{"updated_at":"2023-12-12T12:33:18+08:00","comment":null,"tags":[],"subject_id":441795,"vol_status":0,"ep_status":0,"subject_type":2,"type":3,"rate":0,"private":false,"date":"2024-01-06","images":{"small":"https://lain.bgm.tv/r/200/pic/cover/l/ba/7e/441795_q6Sc3.jpg","grid":"https://lain.bgm.tv/r/100/pic/cover/l/ba/7e/441795_q6Sc3.jpg","large":"https://lain.bgm.tv/pic/cover/l/ba/7e/441795_q6Sc3.jpg","medium":"https://lain.bgm.tv/r/800/pic/cover/l/ba/7e/441795_q6Sc3.jpg","common":"https://lain.bgm.tv/r/400/pic/cover/l/ba/7e/441795_q6Sc3.jpg"},"name":"僕の心のヤバイやつ 第2期","name_cn":"我心里危险的东西 第二季","summary":"重度の中二病で陰キャの市川京太郎と、\r\nクラスで人気者の山田杏奈。\r\n \r\n美少女らしからぬ行動を繰り出す山田に、\r\n市川は目を離せずにいた。\r\n \r\nそんな市川の恋心を知ってか知らずか、\r\n山田は天真爛漫に近づいて来る!!\r\n \r\n全く違う世界にいたはずの2人。\r\nしかしその距離は、徐々に近づいていき……。","total_episodes":12,"eps":0}],"total":7}